[
  {
    "group": "Group H",
    "match": 1,
    "homeTeam": "Spain",
    "awayTeam": "Cape Verde",
    "expGoalsHome": 1.76,
    "expGoalsAway": 0.75,
    "homeScore": 2,
    "awayScore": 0,
    "pHome": 58.8,
    "pDraw": 28.3,
    "pAway": 12.9,
    "prediction": "Spain WIN"
  },
  {
    "group": "Group H",
    "match": 2,
    "homeTeam": "Spain",
    "awayTeam": "Saudi Arabia",
    "expGoalsHome": 1.92,
    "expGoalsAway": 0.68,
    "homeScore": 2,
    "awayScore": 0,
    "pHome": 64.5,
    "pDraw": 25.6,
    "pAway": 9.9,
    "prediction": "Spain WIN"
  },
  {
    "group": "Group H",
    "match": 3,
    "homeTeam": "Spain",
    "awayTeam": "Uruguay",
    "expGoalsHome": 1.49,
    "expGoalsAway": 0.76,
    "homeScore": 1,
    "awayScore": 0,
    "pHome": 51.8,
    "pDraw": 32.2,
    "pAway": 16.0,
    "prediction": "Spain WIN"
  },
  {
    "group": "Group H",
    "match": 4,
    "homeTeam": "Cape Verde",
    "awayTeam": "Saudi Arabia",
    "expGoalsHome": 1.01,
    "expGoalsAway": 0.84,
    "homeScore": 0,
    "awayScore": 0,
    "pHome": 35.3,
    "pDraw": 38.8,
    "pAway": 25.8,
    "prediction": "DRAW"
  },
  {
    "group": "Group H",
    "match": 5,
    "homeTeam": "Cape Verde",
    "awayTeam": "Uruguay",
    "expGoalsHome": 0.79,
    "expGoalsAway": 0.93,
    "homeScore": 0,
    "awayScore": 0,
    "pHome": 25.8,
    "pDraw": 40.2,
    "pAway": 34.0,
    "prediction": "DRAW"
  },
  {
    "group": "Group H",
    "match": 6,
    "homeTeam": "Saudi Arabia",
    "awayTeam": "Uruguay",
    "expGoalsHome": 0.71,
    "expGoalsAway": 1.02,
    "homeScore": 0,
    "awayScore": 0,
    "pHome": 21.7,
    "pDraw": 39.5,
    "pAway": 38.8,
    "prediction": "DRAW"
  }
]